wexample_helpers-0.0.88.dist-info/METADATA
wexample_helpers-0.0.88.dist-info/WHEEL
wexample_helpers-0.0.88.dist-info/entry_points.txt
wexample_helpers/__init__.py
wexample_helpers/__pycache__/__init__.py
wexample_helpers/classes/__init__.py
wexample_helpers/classes/__pycache__/__init__.py
wexample_helpers/classes/abstract_method.py
wexample_helpers/classes/base_class.py
wexample_helpers/classes/base_field.py
wexample_helpers/classes/example/__init__.py
wexample_helpers/classes/example/example.py
wexample_helpers/classes/example/executor.py
wexample_helpers/classes/field.py
wexample_helpers/classes/mixin/__init__.py
wexample_helpers/classes/mixin/__pycache__/__init__.py
wexample_helpers/classes/mixin/has_class_dependencies.py
wexample_helpers/classes/mixin/has_env_keys.py
wexample_helpers/classes/mixin/has_env_keys_file.py
wexample_helpers/classes/mixin/has_log_handler.py
wexample_helpers/classes/mixin/has_short_class_name_class_mixin.py
wexample_helpers/classes/mixin/has_simple_repr_mixin.py
wexample_helpers/classes/mixin/has_snake_short_class_name_class_mixin.py
wexample_helpers/classes/mixin/has_two_steps_init.py
wexample_helpers/classes/mixin/printable_mixin.py
wexample_helpers/classes/mixin/serializable_mixin.py
wexample_helpers/classes/private_field.py
wexample_helpers/classes/protected_field.py
wexample_helpers/classes/shell_result.py
wexample_helpers/common/__init__.py
wexample_helpers/common/__pycache__/__init__.py
wexample_helpers/common/debug/__init__.py
wexample_helpers/common/debug/__pycache__/__init__.py
wexample_helpers/common/debug/abstract_debug.py
wexample_helpers/common/debug/debug_breakpoint.py
wexample_helpers/common/debug/debug_dump.py
wexample_helpers/common/debug/debug_dump_class.py
wexample_helpers/common/debug/debug_trace.py
wexample_helpers/common/exception/__init__.py
wexample_helpers/common/exception/__pycache__/__init__.py
wexample_helpers/common/exception/collector.py
wexample_helpers/common/exception/formatter.py
wexample_helpers/common/exception/frame.py
wexample_helpers/common/exception/handler.py
wexample_helpers/const/__init__.py
wexample_helpers-0.0.88.dist-info/RECORD
